netts/__init__.py
netts/analyze.py
netts/cli/__init__.py
netts/cli/app.py
netts/clients.py
netts/config.py
netts/config_file.py
netts/contractions.py
netts/install_models.py
netts/logger.py
netts/netts_types.py
netts/nlp_helper_functions.py
netts/preprocess/__init__.py
netts/preprocess/defaults.py
netts/preprocess/preprocess.py
netts/speech_graph.py
netts/version.py
netts/visualise_paragraph_functions.py
netts-0.3.2.dist-info/LICENSE
netts-0.3.2.dist-info/METADATA
netts-0.3.2.dist-info/WHEEL
netts-0.3.2.dist-info/entry_points.txt
netts-0.3.2.dist-info/RECORD
