Metadata-Version: 2.1
Name: netts
Version: 0.3.2
Summary: Toolbox for constructing NETworks of Transcript Semantics.
Home-page: https://github.com/alan-turing-institute/netts
License: GPL-3.0-or-later3
Keywords: NLP,networks,transcribed speech,semantic content,graph theory
Author: Caroline Nettekoven
Author-email: crn29@cantab.ac.uk
Requires-Python: >=3.8,<3.11
Classifier: License :: OSI Approved :: GNU General Public License v3 (GPLv3)
Classifier: License :: Other/Proprietary License
Classifier: Operating System :: MacOS
Classifier: Operating System :: Microsoft :: Windows
Classifier: Operating System :: POSIX :: Linux
Classifier: Programming Language :: Python :: 3
Classifier: Programming Language :: Python :: 3.8
Classifier: Programming Language :: Python :: 3.9
Classifier: Programming Language :: Python :: 3.10
Classifier: Programming Language :: Python :: 3
Classifier: Topic :: Scientific/Engineering
Requires-Dist: gdown (>=4.6.0,<5.0.0)
Requires-Dist: matplotlib (>=3.4.3,<4.0.0)
Requires-Dist: networkx (>=2.6.2,<3.0.0)
Requires-Dist: nltk (>=3.6.2,<4.0.0)
Requires-Dist: numpy (>=1.22.2,<2.0.0)
Requires-Dist: pandas (>=1.3.2,<2.0.0)
Requires-Dist: pydantic[dotenv] (>=1.8.2,<2.0.0)
Requires-Dist: pyopenie (>=0.2.0,<0.3.0)
Requires-Dist: requests (>=2.26.0,<3.0.0)
Requires-Dist: rich (>=13.3.2,<14.0.0)
Requires-Dist: rtoml (>=0.8.0,<0.9.0)
Requires-Dist: stanza (>=1.2.3,<2.0.0)
Requires-Dist: tqdm (>=4.62.2,<5.0.0)
Requires-Dist: typer[all] (>=0.4.1,<0.5.0)
Project-URL: Documentation, https://alan-turing-institute.github.io/netts/
Project-URL: Repository, https://github.com/alan-turing-institute/netts
